[
  {
    "word": 1,
    "data": [1,4,3,4,5,6]
  },
  {
    "word": 2,
    "data": [5,2,4,2,7,4]
  },
  {
    "word": 3,
    "data": [7,4,3,4,2,4]
  },
  {
    "word": 4,
    "data": [4,4,4,0,4,4]
  },
  {
    "word": 5,
    "data": [4,3,4,1,2,4]
  },
  {
    "word": 6,
    "data": [1,3,4,7,7,6]
  },
  {
    "word": 7,
    "data": [2,4,3,4,7,5]
  },
  {
    "word": 8,
    "data": [3,6,9,8,6,4]
  },
  {
    "word": 9,
    "data": [2,4,3,4,6,4]
  },
  {
    "word": 10,
    "data": [7,10,8,9,5,3]
  }
]
